inSis/Infoview.py
inSis/__init__.py
insis-2.0.0.0.dist-info/licenses/LICENSE.txt
insis-2.0.0.0.dist-info/METADATA
insis-2.0.0.0.dist-info/WHEEL
insis-2.0.0.0.dist-info/top_level.txt
insis-2.0.0.0.dist-info/RECORD
